README.rst
setup.py
ssh_proxy.egg-info/PKG-INFO
ssh_proxy.egg-info/SOURCES.txt
ssh_proxy.egg-info/dependency_links.txt
ssh_proxy.egg-info/entry_points.txt
ssh_proxy.egg-info/requires.txt
ssh_proxy.egg-info/top_level.txt
sshproxy/__init__.py
sshproxy/__main__.py
sshproxy/networksetup.py